epics_sumo-4.7.1.dist-info/licenses/LICENSE
sumo/Builds.py
sumo/Config.py
sumo/Dependencies.py
sumo/JSON.py
sumo/ModuleSpec.py
sumo/__init__.py
sumo/cli.py
sumo/complete.py
sumo/configuration_doc.py
sumo/cvs.py
sumo/darcs.py
sumo/fileurl.py
sumo/git.py
sumo/lock.py
sumo/makefile_scan.py
sumo/mercurial.py
sumo/patch.py
sumo/path.py
sumo/repos.py
sumo/subversion.py
sumo/sumo_bin.py
sumo/sumo_doc.py
sumo/sumo_scan.py
sumo/system.py
sumo/tar.py
sumo/utils.py
sumo/data/templates/github/DEPS.DB
sumo/doc/LICENSE
sumo/doc/README.rst
sumo/doc/html/app-usage.html
sumo/doc/html/configuration-files.html
sumo/doc/html/contribute.html
sumo/doc/html/demo.html
sumo/doc/html/dev-usage.html
sumo/doc/html/example-sumo-build-try.html
sumo/doc/html/genindex.html
sumo/doc/html/glossary.html
sumo/doc/html/index.html
sumo/doc/html/introduction.html
sumo/doc/html/ioc.html
sumo/doc/html/license.html
sumo/doc/html/migration-examples.html
sumo/doc/html/modulespecs.html
sumo/doc/html/objects.inv
sumo/doc/html/reference-sumo-scan.html
sumo/doc/html/reference-sumo.html
sumo/doc/html/search.html
sumo/doc/html/searchindex.js
sumo/doc/html/sumo-install.html
sumo/doc/html/_images/Modules-A-changed.png
sumo/doc/html/_images/Modules-Sumo.png
sumo/doc/html/_images/Modules-X-changed.png
sumo/doc/html/_images/Modules-all.png
sumo/doc/html/_images/Modules.png
sumo/doc/html/_images/Sumo-overview.png
sumo/doc/html/_images/logo_hzb_big.png
sumo/doc/html/_sources/app-usage.rst.txt
sumo/doc/html/_sources/configuration-files.rst.txt
sumo/doc/html/_sources/contribute.rst.txt
sumo/doc/html/_sources/demo.rst.txt
sumo/doc/html/_sources/dev-usage.rst.txt
sumo/doc/html/_sources/example-sumo-build-try.rst.txt
sumo/doc/html/_sources/glossary.rst.txt
sumo/doc/html/_sources/index.rst.txt
sumo/doc/html/_sources/introduction.rst.txt
sumo/doc/html/_sources/ioc.rst.txt
sumo/doc/html/_sources/license.rst.txt
sumo/doc/html/_sources/migration-examples.rst.txt
sumo/doc/html/_sources/modulespecs.rst.txt
sumo/doc/html/_sources/reference-sumo-scan.rst.txt
epics_sumo-4.7.1.dist-info/METADATA
epics_sumo-4.7.1.dist-info/WHEEL
epics_sumo-4.7.1.dist-info/entry_points.txt
epics_sumo-4.7.1.dist-info/top_level.txt
epics_sumo-4.7.1.dist-info/RECORD
